detectorclient/__init__.py
detectorclient/client.py
detectorclient/db.py
detectorclient/metrics.py
detectorclient/datasets/__init__.py
detectorclient/datasets/paysim.py
detectorclient-0.1.0.dist-info/METADATA
detectorclient-0.1.0.dist-info/WHEEL
detectorclient-0.1.0.dist-info/top_level.txt
detectorclient-0.1.0.dist-info/RECORD
