Metadata-Version: 2.1
Name: detectorclient
Version: 0.1.0
Summary: Simulator API for communicating with the Fraud Simulator Server
Author-email: Sam Redmond <redmonsam@myvuw.ac.nz>
Classifier: License :: Other/Proprietary License
Classifier: Operating System :: OS Independent
Classifier: Programming Language :: Python
Classifier: Programming Language :: Python :: 3 :: Only
Classifier: Programming Language :: Python :: 3.11
Requires-Python: ~=3.11
Requires-Dist: python-socketio
Requires-Dist: websocket-client
Requires-Dist: sqlalchemy
Requires-Dist: requests
Requires-Dist: mysql-connector-python
Requires-Dist: psutil
Provides-Extra: dev
